onql_ext_sdk/__init__.py
onql_ext_sdk/connection.py
onql_ext_sdk/sdk.py
onql_ext-1.0.3.dist-info/METADATA
onql_ext-1.0.3.dist-info/WHEEL
onql_ext-1.0.3.dist-info/top_level.txt
onql_ext-1.0.3.dist-info/RECORD
